LICENSE
MANIFEST.in
README.rst
requirements.txt
screenshot.png
setup.py
itzodmon/__init__.py
itzodmon/datastore.py
itzodmon/timer.py
itzodmon/version.py
itzodmon/web.py
itzodmon.egg-info/PKG-INFO
itzodmon.egg-info/SOURCES.txt
itzodmon.egg-info/dependency_links.txt
itzodmon.egg-info/entry_points.txt
itzodmon.egg-info/not-zip-safe
itzodmon.egg-info/requires.txt
itzodmon.egg-info/top_level.txt
itzodmon/html/favicon.ico
itzodmon/html/graphs.html
itzodmon/html/index.html
itzodmon/html/css/bootstrap-responsive.css
itzodmon/html/css/bootstrap-responsive.min.css
itzodmon/html/css/bootstrap.css
itzodmon/html/css/bootstrap.min.css
itzodmon/html/css/jquery.jqplot.min.css
itzodmon/html/img/glyphicons-halflings-white.png
itzodmon/html/img/glyphicons-halflings.png
itzodmon/html/js/bootstrap.js
itzodmon/html/js/bootstrap.min.js
itzodmon/html/js/d3.v2.min.js
itzodmon/html/js/jqplot.pieRenderer.min.js
itzodmon/html/js/jquery.jqplot.min.js
itzodmon/html/js/jquery.min.js