Metadata-Version: 1.0
Name: itzodmon
Version: 0.2
Summary: pool.itzod.ru bitcoin mining pool monitor
Home-page: https://github.com/shendo/itzodmon
Author: Steve Henderson
Author-email: steve.henderson@hendotech.com.au
License: GPL
Platform: UNKNOWN
Classifier: Development Status :: 4 - Beta
Classifier: Intended Audience :: Developers
Classifier: Intended Audience :: End Users/Desktop
Classifier: License :: OSI Approved :: GNU General Public License v3 or later (GPLv3+)
Classifier: Operating System :: OS Independent
Classifier: Programming Language :: Python
Classifier: Programming Language :: Python :: 2
Classifier: Programming Language :: Python :: 2.6
Classifier: Programming Language :: Python :: 2.7
Classifier: Topic :: Internet :: WWW/HTTP :: WSGI :: Application
